starbot_datasource/__init__.py
starbot_datasource/config.json
starbot_datasource/core/__init__.py
starbot_datasource/core/config.py
starbot_datasource/core/datasource.py
starbot_datasource/core/event.py
starbot_datasource/core/model.py
starbot_datasource/exception/__init__.py
starbot_datasource/exception/ApiException.py
starbot_datasource/exception/DataSourceException.py
starbot_bilibili_datasource-1.2.2.dist-info/LICENSE
starbot_bilibili_datasource-1.2.2.dist-info/METADATA
starbot_bilibili_datasource-1.2.2.dist-info/WHEEL
starbot_bilibili_datasource-1.2.2.dist-info/RECORD
